<DOMSymbolItem xmlns:xsi="http://www.w3.org/2001/XMLSchema-instance" xmlns="http://ns.adobe.com/xfl/2008/" name="Assets/CTallGlassAssets/Tallglasswater" itemID="5b92bb53-00000a11" lastModified="1511815518">
  <timeline>
    <DOMTimeline name="Tallglasswater">
      <layers>
        <DOMLayer name="Layer_1" color="#00FFFF" current="true" isSelected="true">
          <frames>
            <DOMFrame index="0" keyMode="9728">
              <elements>
                <DOMShape>
                  <fills>
                    <FillStyle index="1">
                      <SolidColor color="#00FFFF" alpha="0.0980392156862745"/>
                    </FillStyle>
                    <FillStyle index="2">
                      <LinearGradient>
                        <matrix>
                          <Matrix a="0.002685546875" d="0.002349853515625" tx="-45.4" ty="76.4"/>
                        </matrix>
                        <GradientEntry color="#C2FFFF" alpha="0.6" ratio="0"/>
                        <GradientEntry color="#EBFFFF" alpha="0.870588235294118" ratio="0.0745098039215686"/>
                        <GradientEntry color="#FFFFFF" ratio="1"/>
                      </LinearGradient>
                    </FillStyle>
                    <FillStyle index="3">
                      <LinearGradient>
                        <matrix>
                          <Matrix a="0.001129150390625" d="0.001739501953125" tx="-46.65" ty="75.5"/>
                        </matrix>
                        <GradientEntry color="#C2FFFF" alpha="0.6" ratio="0"/>
                        <GradientEntry color="#EBFFFF" alpha="0.870588235294118" ratio="0.0745098039215686"/>
                        <GradientEntry color="#FFFFFF" ratio="1"/>
                      </LinearGradient>
                    </FillStyle>
                    <FillStyle index="4">
                      <LinearGradient>
                        <matrix>
                          <Matrix a="0.001739501953125" d="0.0023193359375" tx="-46.15" ty="76.45"/>
                        </matrix>
                        <GradientEntry color="#C2FFFF" alpha="0.6" ratio="0"/>
                        <GradientEntry color="#EBFFFF" alpha="0.870588235294118" ratio="0.0745098039215686"/>
                        <GradientEntry color="#FFFFFF" ratio="1"/>
                      </LinearGradient>
                    </FillStyle>
                  </fills>
                  <edges>
                    <Edge fillStyle1="1" edges="!-967 -1775S2|-951 -1775!-951 -1775|-951 -1721!-951 -1721[-781 -1691 -645 -1704!-645 -1704[-420 -1727 -373 -1721!-373 -1721[-313 -1719 -228 -1691!-228 -1691[-181 -1680 -88 -1650!-88 -1650[162 -1579 372 -1615!372 -1615[476 -1632 681 -1687
!681 -1687[849 -1721 968 -1684!968 -1684|968 1592!968 1592[954 1602 936 1616!936 1616[893 1650 867 1665!867 1665[865 1666 863 1668!863 1668|862 1668!862 1668|857 1670!857 1670[854 1672 851 1673!851 1673[801 1695 719 1712!719 1712[687
 1717 644 1722!644 1722|461 1743!461 1743[453 1744 446 1746!446 1746[396 1751 344 1760!344 1760[328 1763 314 1766!314 1766[229 1773 169 1776!169 1776[-32 1780 -481 1727!-481 1727[-598 1713 -684 1698!-684 1698[-693 1695 -702 1692!-702
 1692[-862 1642 -948 1567!-948 1567[-959 1558 -967 1555!-967 1555|-967 -1775"/>
                    <Edge fillStyle0="1" edges="
!-949 1495S1[-949 1490 -946 1487!-946 1487[-943 1483 -934 1481!-934 1481[-919 1478 -908 1482!-908 1482[-892 1487 -892 1502!-892 1502[-892 1508 -898 1521!-898 1521[-903 1533 -901 1539!-901 1539[-900 1543 -897 1549"/>
                    <Edge fillStyle0="1" fillStyle1="2" edges="
!-897 1549S3[-891 1550 -885 1550!-885 1550|-872 1551!-872 1551[-864 1553 -864 1559!-864 1559[-865 1567 -878 1567!-878 1567|-894 1567"/>
                    <Edge fillStyle1="2" edges="
!-894 1567S2|-903 1567"/>
                    <Edge fillStyle0="1" edges="
!-894 1567S1[-897 1572 -904 1576!-904 1576[-911 1581 -925 1577!-925 1577[-932 1575 -935 1572!-935 1572[-940 1567 -941 1562!-941 1562[-942 1559 -943 1557"/>
                    <Edge fillStyle0="2" fillStyle1="3" edges="
!-923 1490S3[-921 1496 -922 1504!-922 1504|-923 1513"/>
                    <Edge fillStyle1="2" edges="
!-923 1490S2|-915 1490!-915 1490[-904 1492 -904 1499!-904 1499[-905 1503 -912 1508!-912 1508|-923 1513"/>
                    <Edge fillStyle1="3" edges="
!-941 1491S2[-941 1490 -941 1489!-941 1489[-937 1480 -929 1482!-929 1482[-925 1486 -923 1490"/>
                    <Edge fillStyle1="4" edges="
!-949 1495S2[-948 1494 -946 1493!-946 1493[-944 1491 -941 1491"/>
                    <Edge fillStyle0="4" fillStyle1="3" edges="
!-951 1513S3[#FFFC49.3C #5E1.C4 -949 1504!-949 1504|-944 1500!-944 1500[-943 1497 -941 1491"/>
                    <Edge fillStyle1="4" edges="
!-951 1513S2|-951 1507"/>
                    <Edge fillStyle0="1" fillStyle1="4" edges="
!-951 1507S3|-951 1499!-951 1499[-950 1497 -949 1495"/>
                    <Edge fillStyle1="3" edges="
!-951 1528.5S2|-951 1518!-951 1518[-951 1517 -951 1516!-951 1516|-951 1513"/>
                    <Edge fillStyle1="2" edges="
!-951 1538S2|-951 1537!-951 1537[-951 #5FC.27 -951 1528.5"/>
                    <Edge fillStyle0="2" fillStyle1="3" edges="
!-926 1539S3[-929 1539 -932 1539!-932 1539|-948 1535!-948 1535[-950.90625 #5FC.18 -951 1528.5"/>
                    <Edge fillStyle0="1" edges="
!-951 1538S1[-953 1532 -953 1526!-953 1526[-953 1519 -951 1507"/>
                    <Edge fillStyle1="4" edges="
!-922 1539S2|-917 1543"/>
                    <Edge fillStyle1="3" edges="
!-923 1513S2[-923 1519 -914 1526!-914 1526[-916 1535 -919 1537!-919 1537[-920 1538 -922 1539"/>
                    <Edge fillStyle0="4" fillStyle1="2" edges="
!-926 1539S3[-922 1541 -917 1543"/>
                    <Edge fillStyle0="4" fillStyle1="3" edges="
!-922 1539S3[-924 1539 -926 1539"/>
                    <Edge fillStyle1="2" edges="
!-926 1566S2|-933 1560!-933 1560[-934 1559 -935 1559!-935 1559|-943 1557"/>
                    <Edge fillStyle1="4" edges="
!-903 1567S2|-920 1567!-920 1567|-926 1566"/>
                    <Edge fillStyle0="1" fillStyle1="2" edges="
!-943 1557S3|-947 1556!-947 1556[-953 1551 -951 1538"/>
                    <Edge fillStyle0="1" edges="
!-966 1621S1[-957 1624 -947 1627!-947 1627[-957 1620 -966 1613!-966 1613[-966.96875 1613 -967 1612!-967 1612|-967 1621!-967 1621|-966 1621"/>
                    <Edge fillStyle0="4" fillStyle1="2" edges="
!-903 1567S3|-926 1566"/>
                    <Edge fillStyle1="2" edges="
!-917 1543S2[-908 1547 -897 1549"/>
                    <Edge cubics="!372 -1615(;217,-1587 65,-1605 -88,-1650q372 -1615Q162 -1579q-88 -1650);"/>
                    <Edge cubics="!-88 -1650(;-181,-1674 -276,-1714 -373,-1721q-88 -1650Q-181 -1680q-228 -1691Q-313 -1719q-373 -1721);"/>
                    <Edge cubics="!-373 -1721(;-464,-1732 -556,-1714 -645,-1704q-373 -1721Q-420 -1727q-645 -1704);"/>
                    <Edge cubics="!-645 -1704(;-748,-1697 -848,-1704 -951,-1721q-645 -1704Q-781 -1691q-951 -1721);"/>
                    <Edge cubics="!-951 -1721(;-951,-1721 -951,-1775 -951,-1775q-951 -1721 -951 -1775);"/>
                    <Edge cubics="!-967 -1775(;-967,-1775 -951,-1775 -951,-1775q-967 -1775 -951 -1775);"/>
                    <Edge cubics="!968 -1684(;888,-1710 791,-1710 681,-1687q968 -1684Q849 -1721q681 -1687);"/>
                    <Edge cubics="!681 -1687(;544,-1650 441,-1628 372,-1615q681 -1687Q476 -1632q372 -1615);"/>
                    <Edge cubics="!-684 1698(;-614,1711 -547,1719 -481,1727q-684 1698 -481 1727);"/>
                    <Edge cubics="!-481 1727(;-265,1754 -51,1780 169,1776q-481 1727Q-32 1780q169 1776);"/>
                    <Edge cubics="!169 1776(;218,1774 267,1771 314,1766q169 1776 314 1766);"/>
                    <Edge cubics="!719 1712(;764,1704 808,1691 851,1673q719 1712Q801 1695q851 1673);"/>
                    <Edge cubics="!-967 1621(;-966,1621 -966,1621 -966,1621q-967 1621Q-966 1621q-966 1621);"/>
                    <Edge cubics="!461 1743(;522,1736 583,1729 644,1722q461 1743 644 1722);"/>
                    <Edge cubics="!-948 1567(;-878,1628 -791,1664 -702,1692q-948 1567Q-862 1642q-702 1692);"/>
                    <Edge cubics="!344 1760(;379,1754 414,1749 446,1746q344 1760 446 1746);"/>
                    <Edge cubics="!-925 1577(;-929,1576 -932,1575 -935,1572q-925 1577Q-932 1575q-935 1572);"/>
                    <Edge cubics="!-935 1572(;-938,1569 -940,1566 -941,1562q-935 1572Q-940 1567q-941 1562);"/>
                    <Edge cubics="!-946 1487(;-943,1483 -938,1482 -934,1481q-946 1487Q-943 1483q-934 1481);"/>
                    <Edge cubics="!-934 1481(;-925,1479 -916,1479 -908,1482q-934 1481Q-919 1478q-908 1482);"/>
                    <Edge cubics="!-908 1482(;-899,1485 -892,1493 -892,1502q-908 1482Q-892 1487q-892 1502);"/>
                    <Edge cubics="!-892 1502(;-891,1515 -905,1527 -901,1539q-892 1502Q-892 1508q-898 1521Q-903 1533q-901 1539);"/>
                    <Edge cubics="!-904 1576(;-910,1580 -918,1579 -925,1577q-904 1576Q-911 1581q-925 1577);"/>
                    <Edge cubics="!-920 1567(;-922,1566 -924,1566 -926,1566q-920 1567 -926 1566);"/>
                    <Edge cubics="!-915 1490(;-910,1491 -904,1494 -904,1499q-915 1490Q-904 1492q-904 1499);"/>
                    <Edge cubics="!-904 1499(;-905,1504 -909,1506 -912,1508q-904 1499Q-905 1503q-912 1508);"/>
                    <Edge cubics="!-885 1550(;-880,1550 -876,1550 -872,1551q-885 1550 -872 1551);"/>
                    <Edge cubics="!-872 1551(;-868,1552 -864,1555 -864,1559q-872 1551Q-864 1553q-864 1559);"/>
                    <Edge cubics="!-864 1559(;-865,1565 -872,1567 -878,1567q-864 1559Q-865 1567q-878 1567);"/>
                    <Edge cubics="!-941 1489(;-939,1484 -934,1481 -929,1482q-941 1489Q-937 1480q-929 1482);"/>
                    <Edge cubics="!-922 1504(;-922,1507 -923,1510 -923,1513q-922 1504 -923 1513);"/>
                    <Edge cubics="!-923 1513(;-923,1519 -918,1523 -914,1526q-923 1513Q-923 1519q-914 1526);"/>
                    <Edge cubics="!-914 1526(;-915,1530 -916,1535 -919,1537q-914 1526Q-916 1535q-919 1537);"/>
                    <Edge cubics="!-946 1493(;-945,1492 -943,1491 -941,1491q-946 1493Q-944 1491q-941 1491);"/>
                    <Edge cubics="!-949 1495(;-948,1494 -947,1494 -946,1493q-949 1495Q-948 1494q-946 1493);"/>
                    <Edge cubics="!-944 1500(;-943,1498 -942,1495 -941,1491q-944 1500Q-943 1497q-941 1491);"/>
                    <Edge cubics="!-941 1491(;-941,1490 -941,1490 -941,1489q-941 1491Q-941 1490q-941 1489);"/>
                    <Edge cubics="!-951 1518(;-951,1517 -951,1517 -951,1516q-951 1518Q-951 1517q-951 1516);"/>
                    <Edge cubics="!-949 1504(;-949,1504 -944,1500 -944,1500q-949 1504 -944 1500);"/>
                    <Edge cubics="!-951 1507(;-951,1507 -951,1499 -951,1499q-951 1507 -951 1499);"/>
                    <Edge cubics="!-951 1499(;-950,1498 -950,1496 -949,1495q-951 1499Q-950 1497q-949 1495);"/>
                    <Edge cubics="!-923 1490(;-922,1494 -921,1499 -922,1504q-923 1490Q-921 1496q-922 1504);"/>
                    <Edge cubics="!-923 1490(;-923,1490 -915,1490 -915,1490q-923 1490 -915 1490);"/>
                    <Edge cubics="!-929 1482(;-926,1485 -924,1487 -923,1490q-929 1482Q-925 1486q-923 1490);"/>
                    <Edge cubics="!-949 1495(;-949,1492 -948,1489 -946,1487q-949 1495Q-949 1490q-946 1487);"/>
                    <Edge cubics="!-919 1537(;-920,1538 -921,1538 -922,1539q-919 1537Q-920 1538q-922 1539);"/>
                    <Edge cubics="!-926 1539(;-928,1539 -930,1539 -932,1539q-926 1539Q-929 1539q-932 1539);"/>
                    <Edge cubics="!-922 1539(;-922,1539 -917,1543 -917,1543q-922 1539 -917 1543);"/>
                    <Edge cubics="!-922 1539(;-923,1539 -925,1539 -926,1539q-922 1539Q-924 1539q-926 1539);"/>
                    <Edge cubics="!-926 1539(;-923,1540 -920,1542 -917,1543q-926 1539Q-922 1541q-917 1543);"/>
                    <Edge cubics="!-951 1538(;-951,1538 -951,1537 -951,1537q-951 1538 -951 1537);"/>
                    <Edge cubics="!-951 1538(;-952,1534 -953,1530 -953,1526q-951 1538Q-953 1532q-953 1526);"/>
                    <Edge cubics="!-943 1557(;-943,1557 -947,1556 -947,1556q-943 1557 -947 1556);"/>
                    <Edge cubics="!-941 1562(;-942,1560 -942,1558 -943,1557q-941 1562Q-942 1559q-943 1557);"/>
                    <Edge cubics="!-926 1566(;-926,1566 -933,1560 -933,1560q-926 1566 -933 1560);"/>
                    <Edge cubics="!-933 1560(;-934,1559 -934,1559 -935,1559q-933 1560Q-934 1559q-935 1559);"/>
                    <Edge cubics="!-932 1539(;-932,1539 -948,1535 -948,1535q-932 1539 -948 1535);"/>
                    <Edge cubics="!-947 1556(;-951,1553 -952,1547 -951,1538q-947 1556Q-953 1551q-951 1538);"/>
                    <Edge cubics="!-935 1559(;-935,1559 -943,1557 -943,1557q-935 1559 -943 1557);"/>
                    <Edge cubics="!-966 1613(;-967,1613 -967,1613 -967,1612q-966 1613Q-967 1613q-967 1612);"/>
                    <Edge cubics="!-967 1612(;-967,1612 -967,1621 -967,1621q-967 1612 -967 1621);"/>
                    <Edge cubics="!-948 1567(;-955,1561 -962,1557 -967,1555q-948 1567Q-959 1558q-967 1555);"/>
                    <Edge cubics="!-966 1621(;-960,1623 -954,1625 -947,1627q-966 1621Q-957 1624q-947 1627);"/>
                    <Edge cubics="!-947 1627(;-954,1622 -960,1618 -966,1613q-947 1627Q-957 1620q-966 1613);"/>
                    <Edge cubics="!-953 1526(;-953,1521 -952,1515 -951,1507q-953 1526Q-953 1519q-951 1507);"/>
                    <Edge cubics="!-901 1539(;-900,1542 -899,1545 -897,1549q-901 1539Q-900 1543q-897 1549);"/>
                    <Edge cubics="!-894 1567(;-896,1570 -899,1573 -904,1576q-894 1567Q-897 1572q-904 1576);"/>
                    <Edge cubics="!-894 1567(;-894,1567 -903,1567 -903,1567q-894 1567 -903 1567);"/>
                    <Edge cubics="!-897 1549(;-893,1550 -889,1550 -885,1550q-897 1549Q-891 1550q-885 1550);"/>
                    <Edge cubics="!-878 1567(;-878,1567 -894,1567 -894,1567q-878 1567 -894 1567);"/>
                    <Edge cubics="!-912 1508(;-912,1508 -923,1513 -923,1513q-912 1508 -923 1513);"/>
                    <Edge cubics="!-917 1543(;-911,1546 -904,1548 -897,1549q-917 1543Q-908 1547q-897 1549);"/>
                    <Edge cubics="!-903 1567(;-903,1567 -926,1566 -926,1566q-903 1567 -926 1566);"/>
                    <Edge cubics="!-684 1698(;-690,1696 -696,1694 -702,1692q-684 1698Q-693 1695q-702 1692);"/>
                    <Edge cubics="!461 1743(;456,1744 451,1745 446,1746q461 1743Q453 1744q446 1746);"/>
                    <Edge cubics="!344 1760(;333,1762 323,1764 314,1766q344 1760Q328 1763q314 1766);"/>
                    <Edge cubics="!968 1592(;959,1599 948,1607 936,1616q968 1592Q954 1602q936 1616);"/>
                    <Edge cubics="!936 1616(;907,1639 884,1655 867,1665q936 1616Q893 1650q867 1665);"/>
                    <Edge cubics="!867 1665(;866,1666 864,1667 863,1668q867 1665Q865 1666q863 1668);"/>
                    <Edge cubics="!863 1668(;863,1668 862,1668 862,1668q863 1668 862 1668);"/>
                    <Edge cubics="!862 1668(;862,1668 857,1670 857,1670q862 1668 857 1670);"/>
                    <Edge cubics="!857 1670(;855,1671 853,1672 851,1673q857 1670Q854 1672q851 1673);"/>
                    <Edge cubics="!719 1712(;698,1715 673,1719 644,1722q719 1712Q687 1717q644 1722);"/>
                    <Edge cubics="!968 -1684(;968,-1684 968,1592 968,1592q968 -1684 968 1592);"/>
                    <Edge cubics="!-967 1555(;-967,1555 -967,-1775 -967,-1775q-967 1555 -967 -1775);"/>
                    <Edge cubics="!-951 1513(;-951,1513 -951,1507 -951,1507q-951 1513 -951 1507);"/>
                    <Edge cubics="!-951 1513(;-951,1508 -950,1505 -949,1504q-951 1513Q-951 1506q-949 1504);"/>
                    <Edge cubics="!-948 1535(;-950,1533 -951,1531 -951,1529q-948 1535Q-951 1532q-951 1529);"/>
                    <Edge cubics="!-951 1537(;-951,1534 -951,1531 -951,1529q-951 1537Q-951 1532q-951 1529);"/>
                    <Edge cubics="!-951 1529(;-951,1529 -951,1518 -951,1518q-951 1529 -951 1518);"/>
                    <Edge cubics="!-951 1516(;-951,1516 -951,1513 -951,1513q-951 1516 -951 1513);"/>
                    <Edge cubics="!-903 1567(;-903,1567 -920,1567 -920,1567q-903 1567 -920 1567);"/>
                  </edges>
                </DOMShape>
              </elements>
            </DOMFrame>
          </frames>
        </DOMLayer>
      </layers>
    </DOMTimeline>
  </timeline>
</DOMSymbolItem>